[{"ID": "108809591N", "Name": "SAMUEL LOCKWOOD", "House": "SPENCER", "TotalLaps": 128, "TotalMetres": 38400, "TotalKm": 38.4}, {"ID": "106381090A", "Name": "XANDER LEONG", "House": "SPENCER", "TotalLaps": 111, "TotalMetres": 33300, "TotalKm": 33.3}, {"ID": "107316215A", "Name": "ARCHIE COOK", "House": "YORKE", "TotalLaps": 101, "TotalMetres": 30300, "TotalKm": 30.3}, {"ID": "108108079M", "Name": "OSCAR BRAY", "House": "YORKE", "TotalLaps": 96, "TotalMetres": 28800, "TotalKm": 28.8}, {"ID": "108983347F", "Name": "JAX MCBEY", "House": "YORKE", "TotalLaps": 88, "TotalMetres": 26400, "TotalKm": 26.4}, {"ID": "108974222X", "Name": "ALEXANDER SHORT", "House": "SPENCER", "TotalLaps": 85, "TotalMetres": 25500, "TotalKm": 25.5}, {"ID": "108529151N", "Name": "CHARLIE HOYLE", "House": "YORKE", "TotalLaps": 84, "TotalMetres": 25200, "TotalKm": 25.2}, {"ID": "107573096L", "Name": "PEARL PEDLER", "House": "SPENCER", "TotalLaps": 82, "TotalMetres": 24600, "TotalKm": 24.6}, {"ID": "107164332X", "Name": "ALEXIS LEONG", "House": "SPENCER", "TotalLaps": 80, "TotalMetres": 24000, "TotalKm": 24.0}, {"ID": "106513053K", "Name": "LIAM PLUTA", "House": "SPENCER", "TotalLaps": 75, "TotalMetres": 22500, "TotalKm": 22.5}, {"ID": "108469647F", "Name": "NATE MODRA", "House": "VINCENT", "TotalLaps": 75, "TotalMetres": 22500, "TotalKm": 22.5}, {"ID": "108238581N", "Name": "RYELEY DUTSCHKE", "House": "SPENCER", "TotalLaps": 72, "TotalMetres": 21600, "TotalKm": 21.6}, {"ID": "108904914P", "Name": "HURLEY CRANWELL", "House": "YORKE", "TotalLaps": 71, "TotalMetres": 21300, "TotalKm": 21.3}, {"ID": "108935282X", "Name": "KIRA WEIR", "House": "YORKE", "TotalLaps": 71, "TotalMetres": 21300, "TotalKm": 21.3}, {"ID": "107968371N", "Name": "NATE KEAN", "House": "VINCENT", "TotalLaps": 69, "TotalMetres": 20700, "TotalKm": 20.7}, {"ID": "108412458T", "Name": "HUGH GERMAINE", "House": "VINCENT", "TotalLaps": 66, "TotalMetres": 19800, "TotalKm": 19.8}, {"ID": "107583888T", "Name": "LEO GLAZBROOK", "House": "SPENCER", "TotalLaps": 62, "TotalMetres": 18600, "TotalKm": 18.6}, {"ID": "107687167F", "Name": "ELI TAYLOR", "House": "YORKE", "TotalLaps": 62, "TotalMetres": 18600, "TotalKm": 18.6}, {"ID": "106913282X", "Name": "OWEN ROHDE", "House": "SPENCER", "TotalLaps": 61, "TotalMetres": 18300, "TotalKm": 18.3}, {"ID": "108422403K", "Name": "RORY BRAY", "House": "YORKE", "TotalLaps": 59, "TotalMetres": 17700, "TotalKm": 17.7}, {"ID": "108034431N", "Name": "MAEVE HONNER", "House": "SPENCER", "TotalLaps": 57, "TotalMetres": 17100, "TotalKm": 17.1}, {"ID": "107342835A", "Name": "WILLIAM MCDONALD", "House": "VINCENT", "TotalLaps": 55, "TotalMetres": 16500, "TotalKm": 16.5}, {"ID": "107669819M", "Name": "JAMES HONNER", "House": "SPENCER", "TotalLaps": 54, "TotalMetres": 16200, "TotalKm": 16.2}, {"ID": "108119475A", "Name": "SIDNEY MCDONALD", "House": "VINCENT", "TotalLaps": 54, "TotalMetres": 16200, "TotalKm": 16.2}, {"ID": "108057524P", "Name": "BROCK REDDING", "House": "YORKE", "TotalLaps": 53, "TotalMetres": 15900, "TotalKm": 15.9}, {"ID": "108045090A", "Name": "MAX KNEEBONE", "House": "SPENCER", "TotalLaps": 52, "TotalMetres": 15600, "TotalKm": 15.6}, {"ID": "107366808T", "Name": "HARRISON BRAY", "House": "YORKE", "TotalLaps": 52, "TotalMetres": 15600, "TotalKm": 15.6}, {"ID": "108569818T", "Name": "KYDEN MAY", "House": "SPENCER", "TotalLaps": 50, "TotalMetres": 15000, "TotalKm": 15.0}, {"ID": "108119402X", "Name": "PAIGE MOORE", "House": "VINCENT", "TotalLaps": 50, "TotalMetres": 15000, "TotalKm": 15.0}, {"ID": "109704809M", "Name": "MAGGIE SHORT", "House": "SPENCER", "TotalLaps": 49, "TotalMetres": 14700, "TotalKm": 14.7}, {"ID": "107692478T", "Name": "RUBY PETERSON", "House": "SPENCER", "TotalLaps": 48, "TotalMetres": 14400, "TotalKm": 14.4}, {"ID": "107096171N", "Name": "ISABELLA EDWARDS", "House": "SPENCER", "TotalLaps": 46, "TotalMetres": 13800, "TotalKm": 13.8}, {"ID": "109127565A", "Name": "MAXWELL BRAY", "House": "YORKE", "TotalLaps": 45, "TotalMetres": 13500, "TotalKm": 13.5}, {"ID": "107704918T", "Name": "LILA SHORT", "House": "YORKE", "TotalLaps": 45, "TotalMetres": 13500, "TotalKm": 13.5}, {"ID": "108994454P", "Name": "JADEN MUMFORD", "House": "VINCENT", "TotalLaps": 44, "TotalMetres": 13200, "TotalKm": 13.2}, {"ID": "107076473K", "Name": "BELLA WEIR", "House": "YORKE", "TotalLaps": 44, "TotalMetres": 13200, "TotalKm": 13.2}, {"ID": "108904594P", "Name": "BRYCE CRANWELL", "House": "YORKE", "TotalLaps": 41, "TotalMetres": 12300, "TotalKm": 12.3}, {"ID": "107892396L", "Name": "WILLIAM COOK", "House": "SPENCER", "TotalLaps": 40, "TotalMetres": 12000, "TotalKm": 12.0}, {"ID": "108275540J", "Name": "OTIS HARRIS", "House": "VINCENT", "TotalLaps": 40, "TotalMetres": 12000, "TotalKm": 12.0}, {"ID": "107703553K", "Name": "RUBI HUMPHRYS", "House": "VINCENT", "TotalLaps": 40, "TotalMetres": 12000, "TotalKm": 12.0}, {"ID": "107677322X", "Name": "NATE REDDING", "House": "YORKE", "TotalLaps": 40, "TotalMetres": 12000, "TotalKm": 12.0}, {"ID": "106849974P", "Name": "BAILLIE BENNETT", "House": "SPENCER", "TotalLaps": 39, "TotalMetres": 11700, "TotalKm": 11.7}, {"ID": "109285924P", "Name": "ROSIE COCK", "House": "SPENCER", "TotalLaps": 39, "TotalMetres": 11700, "TotalKm": 11.7}, {"ID": "109494666L", "Name": "ARYANDEEP SINGH", "House": "VINCENT", "TotalLaps": 39, "TotalMetres": 11700, "TotalKm": 11.7}, {"ID": "106634489M", "Name": "OLIVER CLELAND", "House": "SPENCER", "TotalLaps": 38, "TotalMetres": 11400, "TotalKm": 11.4}, {"ID": "107689044P", "Name": "DELTA REYNOLDS", "House": "SPENCER", "TotalLaps": 38, "TotalMetres": 11400, "TotalKm": 11.4}, {"ID": "107165365A", "Name": "ROSE GIBSON", "House": "YORKE", "TotalLaps": 38, "TotalMetres": 11400, "TotalKm": 11.4}, {"ID": "110079150A", "Name": "OLLIE COCK", "House": "SPENCER", "TotalLaps": 37, "TotalMetres": 11100, "TotalKm": 11.1}, {"ID": "108736766L", "Name": "PENELOPE KOKAR", "House": "YORKE", "TotalLaps": 37, "TotalMetres": 11100, "TotalKm": 11.1}, {"ID": "108646700J", "Name": "MAGGIE COCK", "House": "SPENCER", "TotalLaps": 36, "TotalMetres": 10800, "TotalKm": 10.8}, {"ID": "107150978T", "Name": "LIAM ROHDE", "House": "SPENCER", "TotalLaps": 36, "TotalMetres": 10800, "TotalKm": 10.8}, {"ID": "106171177F", "Name": "REGAN MODRA", "House": "VINCENT", "TotalLaps": 36, "TotalMetres": 10800, "TotalKm": 10.8}, {"ID": "106378698T", "Name": "ALEXANDER REDDING", "House": "YORKE", "TotalLaps": 36, "TotalMetres": 10800, "TotalKm": 10.8}, {"ID": "108108018T", "Name": "NATE HARRIS", "House": "SPENCER", "TotalLaps": 35, "TotalMetres": 10500, "TotalKm": 10.5}, {"ID": "107308160J", "Name": "AMOS HOLLAND", "House": "VINCENT", "TotalLaps": 35, "TotalMetres": 10500, "TotalKm": 10.5}, {"ID": "107869934P", "Name": "SKYLAH SANSBURY", "House": "VINCENT", "TotalLaps": 35, "TotalMetres": 10500, "TotalKm": 10.5}, {"ID": "106627032X", "Name": "HALLE MAY", "House": "VINCENT", "TotalLaps": 34, "TotalMetres": 10200, "TotalKm": 10.2}, {"ID": "109209189M", "Name": "LUCY BRAY", "House": "YORKE", "TotalLaps": 34, "TotalMetres": 10200, "TotalKm": 10.2}, {"ID": "106917220J", "Name": "ZOE BUTTON", "House": "YORKE", "TotalLaps": 34, "TotalMetres": 10200, "TotalKm": 10.2}, {"ID": "105696389M", "Name": "AXEL COCK-LEHMANN", "House": "YORKE", "TotalLaps": 34, "TotalMetres": 10200, "TotalKm": 10.2}, {"ID": "107451923K", "Name": "JAMES MAHAR", "House": "YORKE", "TotalLaps": 34, "TotalMetres": 10200, "TotalKm": 10.2}, {"ID": "105934126L", "Name": "BRIGETTE REDDING", "House": "YORKE", "TotalLaps": 34, "TotalMetres": 10200, "TotalKm": 10.2}, {"ID": "108487849M", "Name": "HARRISON JUDD", "House": "SPENCER", "TotalLaps": 33, "TotalMetres": 9900, "TotalKm": 9.9}, {"ID": "108010445A", "Name": "NATHANIEL SHEARER", "House": "VINCENT", "TotalLaps": 33, "TotalMetres": 9900, "TotalKm": 9.9}, {"ID": "107237408T", "Name": "SUMMER BENVEGNU", "House": "YORKE", "TotalLaps": 33, "TotalMetres": 9900, "TotalKm": 9.9}, {"ID": "110542580J", "Name": "Lillian Jamieson", "House": "VINCENT", "TotalLaps": 31, "TotalMetres": 9300, "TotalKm": 9.3}, {"ID": "107007295A", "Name": "CHARLEE JONES", "House": "VINCENT", "TotalLaps": 31, "TotalMetres": 9300, "TotalKm": 9.3}, {"ID": "108112935A", "Name": "HENRY GIBSON", "House": "YORKE", "TotalLaps": 31, "TotalMetres": 9300, "TotalKm": 9.3}, {"ID": "107176320A", "Name": "LARA COOK", "House": "SPENCER", "TotalLaps": 30, "TotalMetres": 9000, "TotalKm": 9.0}, {"ID": "109357070J", "Name": "ELIJAH NORTON", "House": "SPENCER", "TotalLaps": 30, "TotalMetres": 9000, "TotalKm": 9.0}, {"ID": "107378567F", "Name": "EDWARD SIMONS", "House": "VINCENT", "TotalLaps": 30, "TotalMetres": 9000, "TotalKm": 9.0}, {"ID": "108021994P", "Name": "ZARA THOMAS", "House": "SPENCER", "TotalLaps": 29, "TotalMetres": 8700, "TotalKm": 8.7}, {"ID": "108869133K", "Name": "HUDSON AISH", "House": "VINCENT", "TotalLaps": 29, "TotalMetres": 8700, "TotalKm": 8.7}, {"ID": "107825833K", "Name": "HARRIET MARUSARZ", "House": "YORKE", "TotalLaps": 29, "TotalMetres": 8700, "TotalKm": 8.7}, {"ID": "108119278T", "Name": "MIA VOIGT", "House": "YORKE", "TotalLaps": 29, "TotalMetres": 8700, "TotalKm": 8.7}, {"ID": "107731080A", "Name": "LIVIA PLUTA", "House": "SPENCER", "TotalLaps": 28, "TotalMetres": 8400, "TotalKm": 8.4}, {"ID": "109279200A", "Name": "CHARLIE HILLS", "House": "VINCENT", "TotalLaps": 28, "TotalMetres": 8400, "TotalKm": 8.4}, {"ID": "107200360J", "Name": "DYLAN THOMPSON", "House": "SPENCER", "TotalLaps": 27, "TotalMetres": 8100, "TotalKm": 8.1}, {"ID": "107209888T", "Name": "HENLEY DUTSCHKE", "House": "SPENCER", "TotalLaps": 24, "TotalMetres": 7200, "TotalKm": 7.2}, {"ID": "109222384P", "Name": "Alfie Fitzgerald", "House": "SPENCER", "TotalLaps": 24, "TotalMetres": 7200, "TotalKm": 7.2}, {"ID": "108017864P", "Name": "EVIE MAY", "House": "VINCENT", "TotalLaps": 24, "TotalMetres": 7200, "TotalKm": 7.2}, {"ID": "108575481N", "Name": "JOSIE COOK", "House": "YORKE", "TotalLaps": 24, "TotalMetres": 7200, "TotalKm": 7.2}, {"ID": "108422532X", "Name": "SOPHIE CROSS", "House": "YORKE", "TotalLaps": 24, "TotalMetres": 7200, "TotalKm": 7.2}, {"ID": "109652488T", "Name": "LACHLAN HUDSON", "House": "YORKE", "TotalLaps": 24, "TotalMetres": 7200, "TotalKm": 7.2}, {"ID": "107986886L", "Name": "HARPER MAYWALD", "House": "VINCENT", "TotalLaps": 22, "TotalMetres": 6600, "TotalKm": 6.6}, {"ID": "107611185A", "Name": "AYLA CRANWELL", "House": "YORKE", "TotalLaps": 22, "TotalMetres": 6600, "TotalKm": 6.6}, {"ID": "108570196L", "Name": "RHETT WILLIAMS", "House": "SPENCER", "TotalLaps": 21, "TotalMetres": 6300, "TotalKm": 6.3}, {"ID": "108367041N", "Name": "MARLIE JEFFREY", "House": "VINCENT", "TotalLaps": 21, "TotalMetres": 6300, "TotalKm": 6.3}, {"ID": "108392431N", "Name": "MITCHELL COOK", "House": "YORKE", "TotalLaps": 21, "TotalMetres": 6300, "TotalKm": 6.3}, {"ID": "106946854P", "Name": "JAKOB HOYLE", "House": "YORKE", "TotalLaps": 21, "TotalMetres": 6300, "TotalKm": 6.3}, {"ID": "108112660A", "Name": "DEXTER KOKAR", "House": "YORKE", "TotalLaps": 21, "TotalMetres": 6300, "TotalKm": 6.3}, {"ID": "107338510A", "Name": "GEORGE PREEDY", "House": "YORKE", "TotalLaps": 21, "TotalMetres": 6300, "TotalKm": 6.3}, {"ID": "107795260A", "Name": "CELESTE REDDING", "House": "YORKE", "TotalLaps": 21, "TotalMetres": 6300, "TotalKm": 6.3}, {"ID": "108825450J", "Name": "MITCHELL BRAY", "House": "VINCENT", "TotalLaps": 20, "TotalMetres": 6000, "TotalKm": 6.0}, {"ID": "107652782X", "Name": "AVALEN GERMAINE", "House": "VINCENT", "TotalLaps": 20, "TotalMetres": 6000, "TotalKm": 6.0}, {"ID": "109482735A", "Name": "SUMMER HUMPHRYS", "House": "VINCENT", "TotalLaps": 20, "TotalMetres": 6000, "TotalKm": 6.0}, {"ID": "109652685A", "Name": "MAISON DARDIK", "House": "YORKE", "TotalLaps": 20, "TotalMetres": 6000, "TotalKm": 6.0}, {"ID": "106306261N", "Name": "RILEY STUBBERFIELD", "House": "YORKE", "TotalLaps": 20, "TotalMetres": 6000, "TotalKm": 6.0}, {"ID": "109355328T", "Name": "ERIC DODD", "House": "SPENCER", "TotalLaps": 19, "TotalMetres": 5700, "TotalKm": 5.7}, {"ID": "110621872X", "Name": "JAKOB LOCKWOOD", "House": "SPENCER", "TotalLaps": 19, "TotalMetres": 5700, "TotalKm": 5.7}, {"ID": "109539375A", "Name": "ZARA HUMPHRYS", "House": "VINCENT", "TotalLaps": 19, "TotalMetres": 5700, "TotalKm": 5.7}, {"ID": "109540755A", "Name": "HARLEE MOORE", "House": "VINCENT", "TotalLaps": 19, "TotalMetres": 5700, "TotalKm": 5.7}, {"ID": "108006991N", "Name": "JUDD WEIR", "House": "YORKE", "TotalLaps": 19, "TotalMetres": 5700, "TotalKm": 5.7}, {"ID": "106185526L", "Name": "GEORGINA BROWN", "House": "SPENCER", "TotalLaps": 18, "TotalMetres": 5400, "TotalKm": 5.4}, {"ID": "106236580J", "Name": "FINNIAN GLAZBROOK", "House": "SPENCER", "TotalLaps": 18, "TotalMetres": 5400, "TotalKm": 5.4}, {"ID": "106346178T", "Name": "NAIDA COE", "House": "VINCENT", "TotalLaps": 18, "TotalMetres": 5400, "TotalKm": 5.4}, {"ID": "108389426L", "Name": "TULEAH JEFFREY", "House": "VINCENT", "TotalLaps": 18, "TotalMetres": 5400, "TotalKm": 5.4}, {"ID": "109652010J", "Name": "FINN MCDONALD", "House": "VINCENT", "TotalLaps": 18, "TotalMetres": 5400, "TotalKm": 5.4}, {"ID": "108448399M", "Name": "ROSE WILLIAMS", "House": "VINCENT", "TotalLaps": 18, "TotalMetres": 5400, "TotalKm": 5.4}, {"ID": "109934375A", "Name": "INDIA BAILLIE", "House": "YORKE", "TotalLaps": 18, "TotalMetres": 5400, "TotalKm": 5.4}, {"ID": "107538611N", "Name": "DUSTY REDDING", "House": "YORKE", "TotalLaps": 18, "TotalMetres": 5400, "TotalKm": 5.4}, {"ID": "108569799M", "Name": "KIRA LENNERTH", "House": "VINCENT", "TotalLaps": 17, "TotalMetres": 5100, "TotalKm": 5.1}, {"ID": "107164528T", "Name": "BRIDGET COOK", "House": "YORKE", "TotalLaps": 17, "TotalMetres": 5100, "TotalKm": 5.1}, {"ID": "109704662X", "Name": "LACIE MCBEY", "House": "YORKE", "TotalLaps": 17, "TotalMetres": 5100, "TotalKm": 5.1}, {"ID": "106720005A", "Name": "TIDA HOSKIN", "House": "VINCENT", "TotalLaps": 16, "TotalMetres": 4800, "TotalKm": 4.8}, {"ID": "105541590A", "Name": "ALEXIS KRIEG", "House": "VINCENT", "TotalLaps": 16, "TotalMetres": 4800, "TotalKm": 4.8}, {"ID": "108869108T", "Name": "GABRIEL MCWATERS", "House": "SPENCER", "TotalLaps": 15, "TotalMetres": 4500, "TotalKm": 4.5}, {"ID": "107594682X", "Name": "WILLOW SMITH", "House": "SPENCER", "TotalLaps": 15, "TotalMetres": 4500, "TotalKm": 4.5}, {"ID": "110279005A", "Name": "HENRY CROSS", "House": "YORKE", "TotalLaps": 15, "TotalMetres": 4500, "TotalKm": 4.5}, {"ID": "106781477F", "Name": "LEVI DIGBY", "House": "YORKE", "TotalLaps": 15, "TotalMetres": 4500, "TotalKm": 4.5}, {"ID": "109797733K", "Name": "OLIVIA EICHLER", "House": "YORKE", "TotalLaps": 15, "TotalMetres": 4500, "TotalKm": 4.5}, {"ID": "107540342X", "Name": "LOUIS BROWN", "House": "SPENCER", "TotalLaps": 14, "TotalMetres": 4200, "TotalKm": 4.2}, {"ID": "110436899M", "Name": "PAISLEY GREENWOOD", "House": "SPENCER", "TotalLaps": 14, "TotalMetres": 4200, "TotalKm": 4.2}, {"ID": "109209141N", "Name": "LELAND JUDD", "House": "SPENCER", "TotalLaps": 14, "TotalMetres": 4200, "TotalKm": 4.2}, {"ID": "109900323K", "Name": "TOBY JUDD", "House": "SPENCER", "TotalLaps": 14, "TotalMetres": 4200, "TotalKm": 4.2}, {"ID": "106824918T", "Name": "PAXTON PITT", "House": "SPENCER", "TotalLaps": 14, "TotalMetres": 4200, "TotalKm": 4.2}, {"ID": "106613193K", "Name": "EVIE THOMAS", "House": "SPENCER", "TotalLaps": 14, "TotalMetres": 4200, "TotalKm": 4.2}, {"ID": "105938008T", "Name": "TILLI MACGOWAN", "House": "VINCENT", "TotalLaps": 14, "TotalMetres": 4200, "TotalKm": 4.2}, {"ID": "105912379M", "Name": "SIENNA MCDONNELL", "House": "SPENCER", "TotalLaps": 13, "TotalMetres": 3900, "TotalKm": 3.9}, {"ID": "108645451N", "Name": "ARCHER YOUNG", "House": "SPENCER", "TotalLaps": 13, "TotalMetres": 3900, "TotalKm": 3.9}, {"ID": "107047300J", "Name": "KOURTNEY HANLEY-WOODS", "House": "VINCENT", "TotalLaps": 13, "TotalMetres": 3900, "TotalKm": 3.9}, {"ID": "110077235A", "Name": "ADELINE HEWISH", "House": "VINCENT", "TotalLaps": 13, "TotalMetres": 3900, "TotalKm": 3.9}, {"ID": "110544470A", "Name": "George Jamieson", "House": "VINCENT", "TotalLaps": 13, "TotalMetres": 3900, "TotalKm": 3.9}, {"ID": "107881413K", "Name": "TAHLIAH JONES", "House": "VINCENT", "TotalLaps": 13, "TotalMetres": 3900, "TotalKm": 3.9}, {"ID": "109280652X", "Name": "MAGNOLIA NANKIVELL", "House": "VINCENT", "TotalLaps": 13, "TotalMetres": 3900, "TotalKm": 3.9}, {"ID": "108821579M", "Name": "NOAH HARRIS", "House": "SPENCER", "TotalLaps": 12, "TotalMetres": 3600, "TotalKm": 3.6}, {"ID": "109133117F", "Name": "WILLIAM KNEEBONE", "House": "SPENCER", "TotalLaps": 12, "TotalMetres": 3600, "TotalKm": 3.6}, {"ID": "107720537F", "Name": "MADDISON WARRIOR", "House": "YORKE", "TotalLaps": 12, "TotalMetres": 3600, "TotalKm": 3.6}, {"ID": "105617551N", "Name": "ISOBEL COOK", "House": "SPENCER", "TotalLaps": 11, "TotalMetres": 3300, "TotalKm": 3.3}, {"ID": "107793740A", "Name": "LILEE GASKELL", "House": "VINCENT", "TotalLaps": 11, "TotalMetres": 3300, "TotalKm": 3.3}, {"ID": "108565788T", "Name": "LILLY MULLEN", "House": "VINCENT", "TotalLaps": 11, "TotalMetres": 3300, "TotalKm": 3.3}, {"ID": "108935337F", "Name": "LARISSA REDDING", "House": "YORKE", "TotalLaps": 11, "TotalMetres": 3300, "TotalKm": 3.3}, {"ID": "106246825A", "Name": "JORJA BENNETT", "House": "SPENCER", "TotalLaps": 10, "TotalMetres": 3000, "TotalKm": 3.0}, {"ID": "105541712X", "Name": "ANGUS COOTE", "House": "SPENCER", "TotalLaps": 10, "TotalMetres": 3000, "TotalKm": 3.0}, {"ID": "108320110J", "Name": "ELSIE DODD", "House": "SPENCER", "TotalLaps": 10, "TotalMetres": 3000, "TotalKm": 3.0}, {"ID": "105815672X", "Name": "NOAH MACGOWAN", "House": "VINCENT", "TotalLaps": 10, "TotalMetres": 3000, "TotalKm": 3.0}, {"ID": "105701226L", "Name": "ADDISON SANDERCOCK", "House": "VINCENT", "TotalLaps": 10, "TotalMetres": 3000, "TotalKm": 3.0}, {"ID": "106267673K", "Name": "DARCY WALSH", "House": "VINCENT", "TotalLaps": 10, "TotalMetres": 3000, "TotalKm": 3.0}, {"ID": "109585017F", "Name": "BILLY WIESE", "House": "VINCENT", "TotalLaps": 10, "TotalMetres": 3000, "TotalKm": 3.0}, {"ID": "109521267F", "Name": "MADISON LEWIS", "House": "YORKE", "TotalLaps": 10, "TotalMetres": 3000, "TotalKm": 3.0}, {"ID": "109206335A", "Name": "OLIVE REDDING", "House": "YORKE", "TotalLaps": 10, "TotalMetres": 3000, "TotalKm": 3.0}, {"ID": "106271397F", "Name": "LACHLAN LENNERTH", "House": "VINCENT", "TotalLaps": 9, "TotalMetres": 2700, "TotalKm": 2.7}, {"ID": "110007718T", "Name": "ARCHER MOORE", "House": "VINCENT", "TotalLaps": 9, "TotalMetres": 2700, "TotalKm": 2.7}, {"ID": "107342860J", "Name": "XAVIER KOKAR", "House": "YORKE", "TotalLaps": 9, "TotalMetres": 2700, "TotalKm": 2.7}, {"ID": "106906764P", "Name": "AVA TURLEY", "House": "YORKE", "TotalLaps": 9, "TotalMetres": 2700, "TotalKm": 2.7}, {"ID": "109601716L", "Name": "KAIDEN WEIR", "House": "YORKE", "TotalLaps": 9, "TotalMetres": 2700, "TotalKm": 2.7}, {"ID": "105904202X", "Name": "LOGAN CLELAND", "House": "SPENCER", "TotalLaps": 8, "TotalMetres": 2400, "TotalKm": 2.4}, {"ID": "106278779M", "Name": "GEORGE BENNETT", "House": "VINCENT", "TotalLaps": 8, "TotalMetres": 2400, "TotalKm": 2.4}, {"ID": "105251167F", "Name": "HAMISH COOMBE", "House": "VINCENT", "TotalLaps": 8, "TotalMetres": 2400, "TotalKm": 2.4}, {"ID": "104999342X", "Name": "OSCAR MACGOWAN", "House": "VINCENT", "TotalLaps": 8, "TotalMetres": 2400, "TotalKm": 2.4}, {"ID": "109245846L", "Name": "GRACE BENNETT", "House": "YORKE", "TotalLaps": 8, "TotalMetres": 2400, "TotalKm": 2.4}, {"ID": "105975329M", "Name": "MAXWELL HAMILTON", "House": "YORKE", "TotalLaps": 8, "TotalMetres": 2400, "TotalKm": 2.4}, {"ID": "106833964P", "Name": "DESTINY CAMP", "House": "SPENCER", "TotalLaps": 7, "TotalMetres": 2100, "TotalKm": 2.1}, {"ID": "105315548T", "Name": "CLAUDIA SHORT", "House": "SPENCER", "TotalLaps": 7, "TotalMetres": 2100, "TotalKm": 2.1}, {"ID": "104746824P", "Name": "EMMIE SULLIVAN", "House": "SPENCER", "TotalLaps": 7, "TotalMetres": 2100, "TotalKm": 2.1}, {"ID": "107795086L", "Name": "BAILEY AYLING", "House": "YORKE", "TotalLaps": 7, "TotalMetres": 2100, "TotalKm": 2.1}, {"ID": "106965217F", "Name": "CHARLIE BORGMEYER", "House": "YORKE", "TotalLaps": 7, "TotalMetres": 2100, "TotalKm": 2.1}, {"ID": "108391667F", "Name": "WILLIAM SPIERS", "House": "YORKE", "TotalLaps": 7, "TotalMetres": 2100, "TotalKm": 2.1}, {"ID": "106770426L", "Name": "JAYLA WEIR", "House": "YORKE", "TotalLaps": 7, "TotalMetres": 2100, "TotalKm": 2.1}, {"ID": "105356579M", "Name": "CONNOR COOK", "House": "SPENCER", "TotalLaps": 6, "TotalMetres": 1800, "TotalKm": 1.8}, {"ID": "105398706L", "Name": "ANAIS GLAZBROOK", "House": "SPENCER", "TotalLaps": 6, "TotalMetres": 1800, "TotalKm": 1.8}, {"ID": "110865762X", "Name": "MIA GRIFFITHS", "House": "SPENCER", "TotalLaps": 6, "TotalMetres": 1800, "TotalKm": 1.8}, {"ID": "105597180A", "Name": "CHARLIE PHILLIPS", "House": "SPENCER", "TotalLaps": 6, "TotalMetres": 1800, "TotalKm": 1.8}, {"ID": "109222544P", "Name": "ELLA CUNDY", "House": "VINCENT", "TotalLaps": 6, "TotalMetres": 1800, "TotalKm": 1.8}, {"ID": "106009414P", "Name": "ETHAN GRINHAM", "House": "VINCENT", "TotalLaps": 6, "TotalMetres": 1800, "TotalKm": 1.8}, {"ID": "107609048T", "Name": "BRAYDEN KRIEG", "House": "VINCENT", "TotalLaps": 6, "TotalMetres": 1800, "TotalKm": 1.8}, {"ID": "110077991N", "Name": "ELSIE NANKIVELL", "House": "VINCENT", "TotalLaps": 6, "TotalMetres": 1800, "TotalKm": 1.8}, {"ID": "106248505A", "Name": "WILLIAM CRANWELL", "House": "YORKE", "TotalLaps": 6, "TotalMetres": 1800, "TotalKm": 1.8}, {"ID": "110449650J", "Name": "AYLA FANTINEL", "House": "YORKE", "TotalLaps": 6, "TotalMetres": 1800, "TotalKm": 1.8}, {"ID": "106400071N", "Name": "TAYSAN GATES", "House": "YORKE", "TotalLaps": 6, "TotalMetres": 1800, "TotalKm": 1.8}, {"ID": "106834309M", "Name": "LOGAN ORMSBY", "House": "YORKE", "TotalLaps": 6, "TotalMetres": 1800, "TotalKm": 1.8}, {"ID": "108935349M", "Name": "LENNOX STUBBERFIELD", "House": "YORKE", "TotalLaps": 6, "TotalMetres": 1800, "TotalKm": 1.8}, {"ID": "110308447F", "Name": "ADDISON GEARING", "House": "SPENCER", "TotalLaps": 5, "TotalMetres": 1500, "TotalKm": 1.5}, {"ID": "107572573K", "Name": "INDIGO GLAZBROOK", "House": "SPENCER", "TotalLaps": 5, "TotalMetres": 1500, "TotalKm": 1.5}, {"ID": "109728531N", "Name": "HARPER JUDD", "House": "SPENCER", "TotalLaps": 5, "TotalMetres": 1500, "TotalKm": 1.5}, {"ID": "108487942X", "Name": "LEVI JUDD", "House": "SPENCER", "TotalLaps": 5, "TotalMetres": 1500, "TotalKm": 1.5}, {"ID": "110003234P", "Name": "ALUKA MCSKIMMING", "House": "SPENCER", "TotalLaps": 5, "TotalMetres": 1500, "TotalKm": 1.5}, {"ID": "110274058T", "Name": "RYLEE MORRIS", "House": "SPENCER", "TotalLaps": 5, "TotalMetres": 1500, "TotalKm": 1.5}, {"ID": "109480385A", "Name": "CHARLEE ROBINSON", "House": "SPENCER", "TotalLaps": 5, "TotalMetres": 1500, "TotalKm": 1.5}, {"ID": "106817128T", "Name": "SAXON WILLIAMS", "House": "SPENCER", "TotalLaps": 5, "TotalMetres": 1500, "TotalKm": 1.5}, {"ID": "109925089M", "Name": "MASON GERMAINE", "House": "VINCENT", "TotalLaps": 5, "TotalMetres": 1500, "TotalKm": 1.5}, {"ID": "106792572X", "Name": "ARCHIBALD GRINHAM", "House": "VINCENT", "TotalLaps": 5, "TotalMetres": 1500, "TotalKm": 1.5}, {"ID": "104989895A", "Name": "SHANAID SANSBURY", "House": "VINCENT", "TotalLaps": 5, "TotalMetres": 1500, "TotalKm": 1.5}, {"ID": "104990396L", "Name": "AMBER BORGMEYER", "House": "YORKE", "TotalLaps": 5, "TotalMetres": 1500, "TotalKm": 1.5}, {"ID": "108467549M", "Name": "BONNIE CALDER", "House": "YORKE", "TotalLaps": 5, "TotalMetres": 1500, "TotalKm": 1.5}, {"ID": "105997475A", "Name": "BAILEY DUNSTONE", "House": "YORKE", "TotalLaps": 5, "TotalMetres": 1500, "TotalKm": 1.5}, {"ID": "106833811N", "Name": "CASEY STUBBERFIELD", "House": "YORKE", "TotalLaps": 5, "TotalMetres": 1500, "TotalKm": 1.5}, {"ID": "107181039M", "Name": "AMELIA COOK", "House": "SPENCER", "TotalLaps": 4, "TotalMetres": 1200, "TotalKm": 1.2}, {"ID": "105618295A", "Name": "OLIVIA COOK", "House": "SPENCER", "TotalLaps": 4, "TotalMetres": 1200, "TotalKm": 1.2}, {"ID": "107985029M", "Name": "BAILEY SMITH", "House": "SPENCER", "TotalLaps": 4, "TotalMetres": 1200, "TotalKm": 1.2}, {"ID": "109140460A", "Name": "EMILEE BRAY", "House": "VINCENT", "TotalLaps": 4, "TotalMetres": 1200, "TotalKm": 1.2}, {"ID": "110542659M", "Name": "Loretta Jamieson", "House": "VINCENT", "TotalLaps": 4, "TotalMetres": 1200, "TotalKm": 1.2}, {"ID": "109989640A", "Name": "TAI SANSBURY", "House": "VINCENT", "TotalLaps": 4, "TotalMetres": 1200, "TotalKm": 1.2}, {"ID": "105693302X", "Name": "JOSHUA COOK", "House": "YORKE", "TotalLaps": 4, "TotalMetres": 1200, "TotalKm": 1.2}, {"ID": "106848850A", "Name": "RILEY HUGHES", "House": "YORKE", "TotalLaps": 4, "TotalMetres": 1200, "TotalKm": 1.2}, {"ID": "108094114P", "Name": "JAMAINE TAYLOR-SANSBURY", "House": "YORKE", "TotalLaps": 4, "TotalMetres": 1200, "TotalKm": 1.2}, {"ID": "107707423K", "Name": "ALENA VOIGT", "House": "YORKE", "TotalLaps": 4, "TotalMetres": 1200, "TotalKm": 1.2}, {"ID": "105365160A", "Name": "MIA WARRIOR", "House": "YORKE", "TotalLaps": 4, "TotalMetres": 1200, "TotalKm": 1.2}, {"ID": "109538735A", "Name": "ISLA CUNDY", "House": "VINCENT", "TotalLaps": 3, "TotalMetres": 900, "TotalKm": 0.9}, {"ID": "105888793K", "Name": "BRAYDEN SHEARER", "House": "VINCENT", "TotalLaps": 3, "TotalMetres": 900, "TotalKm": 0.9}, {"ID": "109911190J", "Name": "ALIAH DARDIK", "House": "YORKE", "TotalLaps": 3, "TotalMetres": 900, "TotalKm": 0.9}, {"ID": "105749800J", "Name": "BRIANNA WARRIOR", "House": "YORKE", "TotalLaps": 3, "TotalMetres": 900, "TotalKm": 0.9}, {"ID": "105713575A", "Name": "EVALYN MCWATERS", "House": "SPENCER", "TotalLaps": 2, "TotalMetres": 600, "TotalKm": 0.6}, {"ID": "109538711N", "Name": "Indie Randall-Soph", "House": "SPENCER", "TotalLaps": 2, "TotalMetres": 600, "TotalKm": 0.6}, {"ID": "110400356L", "Name": "HALEIGH SOPH", "House": "SPENCER", "TotalLaps": 2, "TotalMetres": 600, "TotalKm": 0.6}, {"ID": "106793810A", "Name": "REGINALD GRINHAM", "House": "VINCENT", "TotalLaps": 2, "TotalMetres": 600, "TotalKm": 0.6}, {"ID": "108563722X", "Name": "ETTA HARRIS", "House": "VINCENT", "TotalLaps": 2, "TotalMetres": 600, "TotalKm": 0.6}, {"ID": "106236426L", "Name": "BILLY HICKMAN", "House": "VINCENT", "TotalLaps": 2, "TotalMetres": 600, "TotalKm": 0.6}, {"ID": "106719946L", "Name": "RUBEE COCK-LEHMANN", "House": "YORKE", "TotalLaps": 2, "TotalMetres": 600, "TotalKm": 0.6}, {"ID": "104749992X", "Name": "JAMES COOK", "House": "YORKE", "TotalLaps": 2, "TotalMetres": 600, "TotalKm": 0.6}, {"ID": "105626596L", "Name": "KAYDENCE ROSSACK", "House": "YORKE", "TotalLaps": 2, "TotalMetres": 600, "TotalKm": 0.6}, {"ID": "108614900A", "Name": "KHWAHISH DANG", "House": "SPENCER", "TotalLaps": 1, "TotalMetres": 300, "TotalKm": 0.3}, {"ID": "110043883K", "Name": "PEYTON VOGELSANG", "House": "SPENCER", "TotalLaps": 1, "TotalMetres": 300, "TotalKm": 0.3}, {"ID": "109046138T", "Name": "ELEANOR LIEBELT", "House": "VINCENT", "TotalLaps": 1, "TotalMetres": 300, "TotalKm": 0.3}, {"ID": "110288536L", "Name": "AVA O'BRIEN", "House": "VINCENT", "TotalLaps": 1, "TotalMetres": 300, "TotalKm": 0.3}, {"ID": "109531814P", "Name": "RILEY PARSONS", "House": "VINCENT", "TotalLaps": 1, "TotalMetres": 300, "TotalKm": 0.3}, {"ID": "105911647F", "Name": "IVY CRANWELL", "House": "YORKE", "TotalLaps": 1, "TotalMetres": 300, "TotalKm": 0.3}, {"ID": "107990906L", "Name": "SAVANNAH MARUSARZ", "House": "YORKE", "TotalLaps": 1, "TotalMetres": 300, "TotalKm": 0.3}, {"ID": "106822789M", "Name": "CAROLYN SPIERS", "House": "YORKE", "TotalLaps": 1, "TotalMetres": 300, "TotalKm": 0.3}, {"ID": "105997950A", "Name": "HARRY DALE", "House": "SPENCER", "TotalLaps": 0, "TotalMetres": 0, "TotalKm": 0.0}, {"ID": "106834487F", "Name": "PAITEN GLAZBROOK", "House": "SPENCER", "TotalLaps": 0, "TotalMetres": 0, "TotalKm": 0.0}, {"ID": "108613350A", "Name": "ARMAAN DANG", "House": "SPENCER", "TotalLaps": 0, "TotalMetres": 0, "TotalKm": 0.0}, {"ID": "106343809M", "Name": "JAXON EAST", "House": "SPENCER", "TotalLaps": 0, "TotalMetres": 0, "TotalKm": 0.0}, {"ID": "106346129M", "Name": "MITCHELL EAST", "House": "SPENCER", "TotalLaps": 0, "TotalMetres": 0, "TotalKm": 0.0}, {"ID": "109209153K", "Name": "LENA JUDD", "House": "SPENCER", "TotalLaps": 0, "TotalMetres": 0, "TotalKm": 0.0}, {"ID": "110450612X", "Name": "OLIVER MAY", "House": "SPENCER", "TotalLaps": 0, "TotalMetres": 0, "TotalKm": 0.0}, {"ID": "104757285A", "Name": "NOAH MCDONNELL", "House": "SPENCER", "TotalLaps": 0, "TotalMetres": 0, "TotalKm": 0.0}, {"ID": "106438048T", "Name": "JETT POLKINGHORNE", "House": "SPENCER", "TotalLaps": 0, "TotalMetres": 0, "TotalKm": 0.0}, {"ID": "104746154P", "Name": "ELIJAH ROTHE", "House": "SPENCER", "TotalLaps": 0, "TotalMetres": 0, "TotalKm": 0.0}, {"ID": "105298399M", "Name": "ELLA THOMPSON", "House": "SPENCER", "TotalLaps": 0, "TotalMetres": 0, "TotalKm": 0.0}, {"ID": "109222415A", "Name": "BEN WHITEHEAD", "House": "SPENCER", "TotalLaps": 0, "TotalMetres": 0, "TotalKm": 0.0}, {"ID": "108453270A", "Name": "ALEXANDER YOUNG", "House": "SPENCER", "TotalLaps": 0, "TotalMetres": 0, "TotalKm": 0.0}, {"ID": "106898366L", "Name": "ESTELLA BARRETT", "House": "VINCENT", "TotalLaps": 0, "TotalMetres": 0, "TotalKm": 0.0}, {"ID": "105365484P", "Name": "TYRONE BROWN", "House": "VINCENT", "TotalLaps": 0, "TotalMetres": 0, "TotalKm": 0.0}, {"ID": "105804878T", "Name": "LOWAN COE", "House": "VINCENT", "TotalLaps": 0, "TotalMetres": 0, "TotalKm": 0.0}, {"ID": "106387044P", "Name": "MADISON GASKELL", "House": "VINCENT", "TotalLaps": 0, "TotalMetres": 0, "TotalKm": 0.0}, {"ID": "105369434P", "Name": "JAIDEN HANLEY-WOODS", "House": "VINCENT", "TotalLaps": 0, "TotalMetres": 0, "TotalKm": 0.0}, {"ID": "108000612X", "Name": "HUNTER HUMPHRYS", "House": "VINCENT", "TotalLaps": 0, "TotalMetres": 0, "TotalKm": 0.0}, {"ID": "106690819M", "Name": "KAYLEE-STARR KEAN", "House": "VINCENT", "TotalLaps": 0, "TotalMetres": 0, "TotalKm": 0.0}, {"ID": "105797742X", "Name": "KYLE KEAN", "House": "VINCENT", "TotalLaps": 0, "TotalMetres": 0, "TotalKm": 0.0}, {"ID": "106333054P", "Name": "TYRA-JADE KEAN", "House": "VINCENT", "TotalLaps": 0, "TotalMetres": 0, "TotalKm": 0.0}, {"ID": "108885250J", "Name": "TYLER LENNERTH", "House": "VINCENT", "TotalLaps": 0, "TotalMetres": 0, "TotalKm": 0.0}, {"ID": "106162248T", "Name": "ANGUS LIEBELT", "House": "VINCENT", "TotalLaps": 0, "TotalMetres": 0, "TotalKm": 0.0}, {"ID": "109188491N", "Name": "ALISON MARTIN", "House": "VINCENT", "TotalLaps": 0, "TotalMetres": 0, "TotalKm": 0.0}, {"ID": "108711618T", "Name": "CLAIRE MARTIN", "House": "VINCENT", "TotalLaps": 0, "TotalMetres": 0, "TotalKm": 0.0}, {"ID": "107333457F", "Name": "DOMINIC MARTIN", "House": "VINCENT", "TotalLaps": 0, "TotalMetres": 0, "TotalKm": 0.0}, {"ID": "107958316L", "Name": "SOPHIE MARTIN", "House": "VINCENT", "TotalLaps": 0, "TotalMetres": 0, "TotalKm": 0.0}, {"ID": "108935988T", "Name": "THOMAS MCDONALD", "House": "VINCENT", "TotalLaps": 0, "TotalMetres": 0, "TotalKm": 0.0}, {"ID": "109992514P", "Name": "SUNNY RIDDY", "House": "VINCENT", "TotalLaps": 0, "TotalMetres": 0, "TotalKm": 0.0}, {"ID": "106378846L", "Name": "AXEL SECKER", "House": "VINCENT", "TotalLaps": 0, "TotalMetres": 0, "TotalKm": 0.0}, {"ID": "109280340A", "Name": "KATHERINE SECKER", "House": "VINCENT", "TotalLaps": 0, "TotalMetres": 0, "TotalKm": 0.0}, {"ID": "109686166L", "Name": "SACHMAN SINGH", "House": "VINCENT", "TotalLaps": 0, "TotalMetres": 0, "TotalKm": 0.0}, {"ID": "105161309M", "Name": "MAGGIE WALSH", "House": "VINCENT", "TotalLaps": 0, "TotalMetres": 0, "TotalKm": 0.0}, {"ID": "105357472X", "Name": "MACKENZIE WHITE", "House": "VINCENT", "TotalLaps": 0, "TotalMetres": 0, "TotalKm": 0.0}, {"ID": "110807605A", "Name": "BOSTON BAILLIE", "House": "YORKE", "TotalLaps": 0, "TotalMetres": 0, "TotalKm": 0.0}, {"ID": "105919020A", "Name": "ELLEY BRYANT", "House": "YORKE", "TotalLaps": 0, "TotalMetres": 0, "TotalKm": 0.0}, {"ID": "109222821N", "Name": "LAYLA CALDER", "House": "YORKE", "TotalLaps": 0, "TotalMetres": 0, "TotalKm": 0.0}, {"ID": "106098302X", "Name": "MADDEN GLOVER", "House": "YORKE", "TotalLaps": 0, "TotalMetres": 0, "TotalKm": 0.0}, {"ID": "108938339M", "Name": "HARVEY GOLDSWORTHY", "House": "YORKE", "TotalLaps": 0, "TotalMetres": 0, "TotalKm": 0.0}, {"ID": "104756516L", "Name": "MITCHELL HAMILTON", "House": "YORKE", "TotalLaps": 0, "TotalMetres": 0, "TotalKm": 0.0}, {"ID": "106643738T", "Name": "FLOREDRE HANSEN", "House": "YORKE", "TotalLaps": 0, "TotalMetres": 0, "TotalKm": 0.0}, {"ID": "109376324P", "Name": "KOLBY LEIBHARDT", "House": "YORKE", "TotalLaps": 0, "TotalMetres": 0, "TotalKm": 0.0}, {"ID": "106315466L", "Name": "LOGAN MAY", "House": "YORKE", "TotalLaps": 0, "TotalMetres": 0, "TotalKm": 0.0}, {"ID": "109653092X", "Name": "SLOANE RADEMACHER", "House": "YORKE", "TotalLaps": 0, "TotalMetres": 0, "TotalKm": 0.0}, {"ID": "109517912X", "Name": "IRIS REDDING", "House": "YORKE", "TotalLaps": 0, "TotalMetres": 0, "TotalKm": 0.0}, {"ID": "110278856L", "Name": "EVIE WALTON-LIDDIARD", "House": "YORKE", "TotalLaps": 0, "TotalMetres": 0, "TotalKm": 0.0}, {"ID": "109843023K", "Name": "HENRY YATES", "House": "YORKE", "TotalLaps": 0, "TotalMetres": 0, "TotalKm": 0.0}]